directinput.py
windirectinput-1.6.1.dist-info/LICENSE
windirectinput-1.6.1.dist-info/METADATA
windirectinput-1.6.1.dist-info/WHEEL
windirectinput-1.6.1.dist-info/top_level.txt
windirectinput-1.6.1.dist-info/RECORD
