Metadata-Version: 2.1
Name: winDirectInput
Version: 1.6.1
Summary: A Windows-specific package for simulating keyboard and mouse inputs
Home-page: https://github.com/abdulrahimpds/winDirectInput
Author: AbdulRahim Khan
Author-email: abdulrahimpds@gmail.com
Classifier: Programming Language :: Python :: 3.8
Classifier: Intended Audience :: Developers
Classifier: License :: OSI Approved :: MIT License
Classifier: Operating System :: Microsoft :: Windows
Requires-Python: >=3.8
License-File: LICENSE
Requires-Dist: opencv-python
Requires-Dist: numpy
Requires-Dist: mss
Requires-Dist: pyscreeze
Requires-Dist: pillow
Requires-Dist: pyperclip
